iitbbscli/__init__.py
iitbbscli/app.py
iitbbscliupdates-0.0.1.dist-info/LICENSE
iitbbscliupdates-0.0.1.dist-info/METADATA
iitbbscliupdates-0.0.1.dist-info/WHEEL
iitbbscliupdates-0.0.1.dist-info/entry_points.txt
iitbbscliupdates-0.0.1.dist-info/top_level.txt
iitbbscliupdates-0.0.1.dist-info/RECORD
