Metadata-Version: 2.1
Name: iitbbscliupdates
Version: 0.0.1
Summary: CLI for IIT Bhubaneswar updates.
Home-page: https://github.com/IronVenom/IIT-Bhubaneswar-CLI
Author: Atharva Kulkarni
Author-email: amk11@iitbbs.ac.in
License: UNKNOWN
Platform: UNKNOWN
Requires-Dist: Click
Requires-Dist: requests
Requires-Dist: bs4
Requires-Dist: prettytable
Requires-Dist: setuptools
Requires-Dist: lxml
